Metadata-Version: 2.4
Name: algozen
Version: 1.2.2
Summary: A comprehensive Python package for Data Structures, Algorithms, Design Patterns, and Problem Solutions
Author-email: moah0911 <stormshots0911@gmail.com>
Maintainer-email: moah0911 <stormshots0911@gmail.com>
License: MIT
Project-URL: Homepage, https://github.com/moah0911/algozen
Project-URL: Repository, https://github.com/moah0911/algozen
Project-URL: Bug Reports, https://github.com/moah0911/algozen/issues
Project-URL: Documentation, https://github.com/moah0911/algozen#readme
Keywords: algorithms,data-structures,computer-science,programming,leetcode,interview,coding,patterns,design-patterns,sorting,searching,graph,tree,dynamic-programming
Classifier: Development Status :: 5 - Production/Stable
Classifier: Intended Audience :: Developers
Classifier: Intended Audience :: Education
Classifier: Intended Audience :: Science/Research
Classifier: License :: OSI Approved :: MIT License
Classifier: Operating System :: OS Independent
Classifier: Programming Language :: Python :: 3
Classifier: Programming Language :: Python :: 3.7
Classifier: Programming Language :: Python :: 3.8
Classifier: Programming Language :: Python :: 3.9
Classifier: Programming Language :: Python :: 3.10
Classifier: Programming Language :: Python :: 3.11
Classifier: Programming Language :: Python :: 3.12
Classifier: Topic :: Software Development :: Libraries :: Python Modules
Classifier: Topic :: Education
Classifier: Topic :: Scientific/Engineering
Classifier: Topic :: Software Development :: Libraries
Requires-Python: >=3.7
License-File: LICENSE
Dynamic: license-file
